MANIFEST.in
README.md
instagram_oauth.py
setup.py
instagram_oauth.egg-info/PKG-INFO
instagram_oauth.egg-info/SOURCES.txt
instagram_oauth.egg-info/dependency_links.txt
instagram_oauth.egg-info/not-zip-safe
instagram_oauth.egg-info/requires.txt
instagram_oauth.egg-info/top_level.txt