Metadata-Version: 1.1
Name: instagram-oauth
Version: 0.1.1
Summary: Instagram API oauth authentication helper
Home-page: https://github.com/gpip/instagram-oauth
Author: Guilherme Polo
Author-email: gp@luster.cc
License: UNKNOWN
Keywords: instagram,oauth,api
Platform: UNKNOWN
Classifier: Intended Audience :: Developers
Classifier: Programming Language :: Python :: 2
Classifier: Programming Language :: Python :: Implementation :: CPython
Classifier: Topic :: Software Development :: Libraries
